LICENSE.txt
MANIFEST.in
README.rst
requirements-test.txt
setup.cfg
setup.py
tox.ini
beem/__init__.py
beem/account.py
beem/amount.py
beem/asciichart.py
beem/asset.py
beem/block.py
beem/blockchain.py
beem/blockchaininstance.py
beem/blockchainobject.py
beem/blurt.py
beem/cli.py
beem/comment.py
beem/community.py
beem/constants.py
beem/conveyor.py
beem/discussions.py
beem/exceptions.py
beem/hive.py
beem/hivesigner.py
beem/imageuploader.py
beem/instance.py
beem/market.py
beem/memo.py
beem/message.py
beem/nodelist.py
beem/price.py
beem/profile.py
beem/rc.py
beem/snapshot.py
beem/steem.py
beem/storage.py
beem/transactionbuilder.py
beem/utils.py
beem/version.py
beem/vote.py
beem/wallet.py
beem/witness.py
beem_blurt_discord.egg-info/PKG-INFO
beem_blurt_discord.egg-info/SOURCES.txt
beem_blurt_discord.egg-info/dependency_links.txt
beem_blurt_discord.egg-info/entry_points.txt
beem_blurt_discord.egg-info/requires.txt
beem_blurt_discord.egg-info/top_level.txt
beemapi/__init__.py
beemapi/exceptions.py
beemapi/graphenerpc.py
beemapi/node.py
beemapi/noderpc.py
beemapi/rpcutils.py
beemapi/version.py
beembase/__init__.py
beembase/ledgertransactions.py
beembase/memo.py
beembase/objects.py
beembase/objecttypes.py
beembase/operationids.py
beembase/operations.py
beembase/operationsidblurt.py
beembase/signedtransactions.py
beembase/transactions.py
beembase/version.py
beemgrapheneapi/__init__.py
beemgraphenebase/__init__.py
beemgraphenebase/account.py
beemgraphenebase/aes.py
beemgraphenebase/base58.py
beemgraphenebase/bip32.py
beemgraphenebase/bip38.py
beemgraphenebase/chains.py
beemgraphenebase/dictionary.py
beemgraphenebase/ecdsasig.py
beemgraphenebase/objects.py
beemgraphenebase/objecttypes.py
beemgraphenebase/operationids.py
beemgraphenebase/operations.py
beemgraphenebase/prefix.py
beemgraphenebase/py23.py
beemgraphenebase/signedtransactions.py
beemgraphenebase/types.py
beemgraphenebase/unsignedtransactions.py
beemgraphenebase/version.py
beemstorage/__init__.py
beemstorage/base.py
beemstorage/exceptions.py
beemstorage/interfaces.py
beemstorage/masterpassword.py
beemstorage/ram.py
beemstorage/sqlite.py
docs/Makefile
docs/apidefinitions.rst
docs/beem.account.rst
docs/beem.amount.rst
docs/beem.asciichart.rst
docs/beem.asset.rst
