Metadata-Version: 2.1
Name: beem-blurt-discord
Version: 0.24.25
Summary: Unofficial Python library for BLURT
Home-page: https://github.com/Damurq/beem/
Author: Holger Nahrstaedt
Author-email: nahrstaedt@gmail.com
Maintainer: Holger Nahrstaedt
Maintainer-email: nahrstaedt@gmail.com
License: UNKNOWN
Download-URL: https://github.com/Damurq/beem/tarball/0.24.25
Keywords: blurt,library,api,rpc
Platform: UNKNOWN
Classifier: License :: OSI Approved :: MIT License
Classifier: Operating System :: OS Independent
Classifier: Programming Language :: Python
Classifier: Programming Language :: Python :: 3
Classifier: Programming Language :: Python :: 3.6
Classifier: Programming Language :: Python :: 3.7
Classifier: Programming Language :: Python :: 3.8
Classifier: Programming Language :: Python :: 3.9
Classifier: Development Status :: 4 - Beta
Classifier: Intended Audience :: Developers
Classifier: Intended Audience :: Financial and Insurance Industry
Classifier: Topic :: Office/Business :: Financial
License-File: LICENSE.txt
